walkman_modules/convolution_reverbs/__init__.py
walkman_modules.convolution_reverb-0.3.0.dist-info/LICENSE
walkman_modules.convolution_reverb-0.3.0.dist-info/METADATA
walkman_modules.convolution_reverb-0.3.0.dist-info/WHEEL
walkman_modules.convolution_reverb-0.3.0.dist-info/top_level.txt
walkman_modules.convolution_reverb-0.3.0.dist-info/RECORD
