Metadata-Version: 2.1
Name: walkman-modules.convolution-reverb
Version: 0.3.0
Summary: Provides walkman module to send input through a convolution reverb
Author: Levin Eric Zimmermann
Author-email: levin.eric.zimmermann@posteo.eu
License: GPL
Requires-Python: ==3.8
License-File: LICENSE
Requires-Dist: audiowalkman (<1.0.0,>=0.11.0)
Requires-Dist: pyo (==1.0.4)
Provides-Extra: testing
Requires-Dist: nose ; extra == 'testing'
